oclc_wrappers/__init__.py
oclc_wrappers/acquisitions.py
oclc_wrappers/auth.py
oclc_wrappers/constants.py
oclc_wrappers/kb.py
oclc_wrappers/oclc_exceptions.py
oclc_wrappers/requestor.py
oclc_wrappers/urlmanager.py
oclc_wrappers/worldcat.py
oclc_wrappers/xmlobject.py
oclc_wrappers/tests/__init__.py
oclc_wrappers/tests/configTest.py
oclc_wrappers/tests/test_item.py
oclc_wrappers/tests/test_purchaseOrder.py
oclc_wrappers/tests/test_requestor.py
oclc_wrappers/tests/test_urls.py
oclc_wrappers/tests/test_worldcatResource.py
oclc_wrappers-0.0.5.dist-info/METADATA
oclc_wrappers-0.0.5.dist-info/RECORD
oclc_wrappers-0.0.5.dist-info/WHEEL
oclc_wrappers-0.0.5.dist-info/top_level.txt
