Metadata-Version: 2.1
Name: oclc-wrappers
Version: 0.0.5
Summary: Wrappers around OCLC APIs
Home-page: https://github.com/pybrarian/oclc_wrappers
Author: Ed Hill
Author-email: edhill@protonmail.com
License: UNKNOWN
Platform: UNKNOWN
Classifier: Programming Language :: Python :: 3
Classifier: Programming Language :: Python :: 2
Classifier: Operating System :: OS Independent
